[
  {
    "run": 6,
    "run_id": "27288593224",
    "date": "2026-06-10 16:03",
    "ref": "main",
    "commit": "c2033fff0d766b0718e856ca60a1588d12324a13",
    "short_commit": "c2033ff",
    "trigger": "workflow_dispatch",
    "release": false,
    "report": "runs/6/",
    "ci_url": "https://github.com/opengeneral/opengeneral/actions/runs/27288593224",
    "passed": 214,
    "failed": 0,
    "skipped": 23,
    "total": 237
  },
  {
    "run": 7,
    "run_id": "27291426834",
    "date": "2026-06-10 16:52",
    "ref": "main",
    "commit": "838d6ef519b3d5518255fad7b94074236836be54",
    "short_commit": "838d6ef",
    "trigger": "workflow_dispatch",
    "release": false,
    "report": "runs/7/",
    "ci_url": "https://github.com/opengeneral/opengeneral/actions/runs/27291426834",
    "passed": 214,
    "failed": 0,
    "skipped": 23,
    "total": 237
  },
  {
    "run": 8,
    "run_id": "27293164113",
    "date": "2026-06-10 17:24",
    "ref": "main",
    "commit": "af4dceb8e629b409389178f13df049d898da4fc7",
    "short_commit": "af4dceb",
    "trigger": "workflow_dispatch",
    "release": false,
    "report": "runs/8/",
    "ci_url": "https://github.com/opengeneral/opengeneral/actions/runs/27293164113",
    "passed": 214,
    "failed": 0,
    "skipped": 29,
    "total": 243
  },
  {
    "run": 9,
    "run_id": "27308753703",
    "date": "2026-06-10 21:58",
    "ref": "main",
    "commit": "74fd3b3426ff1f4d5a78deb7f96f001444a8068d",
    "short_commit": "74fd3b3",
    "trigger": "workflow_dispatch",
    "release": false,
    "report": "runs/9/",
    "ci_url": "https://github.com/opengeneral/opengeneral/actions/runs/27308753703",
    "passed": 214,
    "failed": 0,
    "skipped": 29,
    "total": 243
  },
  {
    "run": 10,
    "run_id": "27316389352",
    "date": "2026-06-11 01:00",
    "ref": "main",
    "commit": "19771079ec33a310a57d8485e7154c6493362e31",
    "short_commit": "1977107",
    "trigger": "workflow_dispatch",
    "release": false,
    "report": "runs/10/",
    "ci_url": "https://github.com/opengeneral/opengeneral/actions/runs/27316389352",
    "passed": 218,
    "failed": 0,
    "skipped": 34,
    "total": 252
  },
  {
    "run": 11,
    "run_id": "27371032679",
    "date": "2026-06-11 19:20",
    "ref": "main",
    "commit": "31871f4cf4a0e60b33a0c87cd41c270bcbe641a3",
    "short_commit": "31871f4",
    "trigger": "workflow_dispatch",
    "release": false,
    "report": "runs/11/",
    "ci_url": "https://github.com/opengeneral/opengeneral/actions/runs/27371032679",
    "passed": 218,
    "failed": 0,
    "skipped": 34,
    "total": 252
  },
  {
    "run": 12,
    "run_id": "27371762494",
    "date": "2026-06-11 19:31",
    "ref": "main",
    "commit": "c91c75fde059d92a46cdf64a8a90dcb36070482e",
    "short_commit": "c91c75f",
    "trigger": "workflow_dispatch",
    "release": false,
    "report": "runs/12/",
    "ci_url": "https://github.com/opengeneral/opengeneral/actions/runs/27371762494",
    "passed": 218,
    "failed": 0,
    "skipped": 34,
    "total": 252
  },
  {
    "run": 13,
    "run_id": "27372404274",
    "date": "2026-06-11 19:42",
    "ref": "main",
    "commit": "20c699ed728b1bca8929869737500c90789b3d79",
    "short_commit": "20c699e",
    "trigger": "workflow_dispatch",
    "release": false,
    "report": "runs/13/",
    "ci_url": "https://github.com/opengeneral/opengeneral/actions/runs/27372404274",
    "passed": 218,
    "failed": 0,
    "skipped": 34,
    "total": 252
  },
  {
    "run": 14,
    "run_id": "27373084764",
    "date": "2026-06-11 19:54",
    "ref": "main",
    "commit": "ba6a6b6945809e3fc524837514b80337e4f4c3fb",
    "short_commit": "ba6a6b6",
    "trigger": "workflow_dispatch",
    "release": false,
    "report": "runs/14/",
    "ci_url": "https://github.com/opengeneral/opengeneral/actions/runs/27373084764",
    "passed": 218,
    "failed": 0,
    "skipped": 34,
    "total": 252
  },
  {
    "run": 15,
    "run_id": "27373480375",
    "date": "2026-06-11 20:04",
    "ref": "main",
    "commit": "441dd4e331749761669449129e633f49efc4ff0b",
    "short_commit": "441dd4e",
    "trigger": "workflow_dispatch",
    "release": false,
    "report": "runs/15/",
    "ci_url": "https://github.com/opengeneral/opengeneral/actions/runs/27373480375",
    "passed": 177,
    "failed": 0,
    "skipped": 11,
    "total": 188
  }
]